LICENSE
MANIFEST.in
README.md
pyproject.toml
requirements.txt
setup.py
map_games_proto.egg-info/PKG-INFO
map_games_proto.egg-info/SOURCES.txt
map_games_proto.egg-info/dependency_links.txt
map_games_proto.egg-info/not-zip-safe
map_games_proto.egg-info/requires.txt
map_games_proto.egg-info/top_level.txt
open_spiel/CMakeLists.txt
open_spiel/__init__.py
open_spiel/action_view.cc
open_spiel/action_view.h
open_spiel/canonical_game_strings.cc
open_spiel/canonical_game_strings.h
open_spiel/game_parameters.cc
open_spiel/game_parameters.h
open_spiel/matrix_game.cc
open_spiel/matrix_game.h
open_spiel/normal_form_game.h
open_spiel/observer.cc
open_spiel/observer.h
open_spiel/policy.cc
open_spiel/policy.h
open_spiel/simultaneous_move_game.cc
open_spiel/simultaneous_move_game.h
open_spiel/spiel.cc
open_spiel/spiel.h
open_spiel/spiel_bots.cc
open_spiel/spiel_bots.h
open_spiel/spiel_globals.h
open_spiel/spiel_utils.cc
open_spiel/spiel_utils.h
open_spiel/tensor_game.cc
open_spiel/tensor_game.h
open_spiel/abseil-cpp/CMakeLists.txt
open_spiel/abseil-cpp/conanfile.py
open_spiel/abseil-cpp/create_lts.py
open_spiel/abseil-cpp/CMake/AbseilDll.cmake
open_spiel/abseil-cpp/CMake/AbseilHelpers.cmake
open_spiel/abseil-cpp/CMake/README.md
open_spiel/abseil-cpp/CMake/abslConfig.cmake.in
open_spiel/abseil-cpp/CMake/Googletest/CMakeLists.txt.in
open_spiel/abseil-cpp/CMake/Googletest/DownloadGTest.cmake
open_spiel/abseil-cpp/CMake/install_test_project/CMakeLists.txt
open_spiel/abseil-cpp/CMake/install_test_project/simple.cc
open_spiel/abseil-cpp/CMake/install_test_project/test.sh
open_spiel/abseil-cpp/absl/CMakeLists.txt
open_spiel/abseil-cpp/absl/abseil.podspec.gen.py
open_spiel/abseil-cpp/absl/algorithm/CMakeLists.txt
open_spiel/abseil-cpp/absl/algorithm/algorithm.h
open_spiel/abseil-cpp/absl/algorithm/algorithm_test.cc
open_spiel/abseil-cpp/absl/algorithm/container.h
open_spiel/abseil-cpp/absl/algorithm/container_test.cc
open_spiel/abseil-cpp/absl/base/CMakeLists.txt
open_spiel/abseil-cpp/absl/base/attributes.h
open_spiel/abseil-cpp/absl/base/bit_cast_test.cc
open_spiel/abseil-cpp/absl/base/call_once.h
open_spiel/abseil-cpp/absl/base/call_once_test.cc
open_spiel/abseil-cpp/absl/base/casts.h
