Metadata-Version: 2.1
Name: map-games-proto
Version: 1.6.8.12
Summary: A Framework for Reinforcement Learning in Games (forked from OpenSpiel)
Author-email: LogitGames <admin@logitgames.com>
License: Apache 2.0
Project-URL: Homepage, https://github.com/logitgames/map_games_proto
Requires-Python: >=3.10
License-File: LICENSE
Requires-Dist: pip>=20.0.2
Requires-Dist: attrs>=19.3.0
Requires-Dist: absl-py>=0.10.0
Requires-Dist: numpy>=1.21.5
Requires-Dist: scipy>=1.10.1
Requires-Dist: ml-collections>=0.1.1
